{
  "version": "7",
  "dialect": "sqlite",
  "entries": [
    {
      "idx": 0,
      "version": "6",
      "when": 1770306454096,
      "tag": "0000_big_kid_colt",
      "breakpoints": true
    },
    {
      "idx": 1,
      "version": "6",
      "when": 1770312554322,
      "tag": "0001_harsh_luke_cage",
      "breakpoints": true
    },
    {
      "idx": 2,
      "version": "6",
      "when": 1770668560283,
      "tag": "0002_smooth_sersi",
      "breakpoints": true
    },
    {
      "idx": 3,
      "version": "6",
      "when": 1771351041588,
      "tag": "0003_warm_pepper_potts",
      "breakpoints": true
    },
    {
      "idx": 4,
      "version": "6",
      "when": 1771003200000,
      "tag": "0004_kb_skywalker",
      "breakpoints": true
    },
    {
      "idx": 5,
      "version": "6",
      "when": 1771360200000,
      "tag": "0005_kb_repair",
      "breakpoints": true
    },
    {
      "idx": 6,
      "version": "6",
      "when": 1771453200000,
      "tag": "0006_kb_document_files",
      "breakpoints": true
    },
    {
      "idx": 7,
      "version": "6",
      "when": 1771456200000,
      "tag": "0007_kb_preview_state",
      "breakpoints": true
    },
    {
      "idx": 8,
      "version": "6",
      "when": 1771478682004,
      "tag": "0008_true_mister_fear",
      "breakpoints": true
    },
    {
      "idx": 9,
      "version": "6",
      "when": 1771543894358,
      "tag": "0009_many_jack_power",
      "breakpoints": true
    },
    {
      "idx": 10,
      "version": "6",
      "when": 1771610575674,
      "tag": "0010_thick_the_spike",
      "breakpoints": true
    },
    {
      "idx": 11,
      "version": "6",
      "when": 1771617168394,
      "tag": "0011_majestic_thundra",
      "breakpoints": true
    },
    {
      "idx": 12,
      "version": "6",
      "when": 1771884164353,
      "tag": "0012_previous_captain_flint",
      "breakpoints": true
    }
  ]
}